{
    "Naruto": {
        "NARUTO": "https://imgur.com/eQa9C6C.png",
        "SASUKE": "https://imgur.com/iUOVSZS.png",

        "KAKASHI": "azeazeazeazeaeaze",
        "ITACHI": "https://imgur.com/z0hiJdF.png",
        "MADARA": "https://imgur.com/XtuhYu5.png",
        "SHISUI": "https://imgur.com/kIAdt34.png",
        "KAGUYA": "https://imgur.com/wFoobmZ.png",
        "HINATA": "https://imgur.com/EcxzKkY.png",
        "SHINO": "https://imgur.com/ZZO5Wjm.png",
        "KIBA": "https://imgur.com/hBsXuHQ.png",
        "JIRAYA": "https://imgur.com/KUHp9tD.png",
        "OROCHIMARU": "https://imgur.com/wLwhaOO.png",
        "TSUNADE": "https://imgur.com/6Q1C0nL.png",
        "TOBIRAMA": "https://imgur.com/3OKcVue.png",
        "HASHIRAMA": "https://imgur.com/bz2tpyI.png",
        "MINATO": "https://imgur.com/oOKAbb5.png",
        "KAKASHI": "https://imgur.com/ugCdchd.png",
        "OBITO": "https://imgur.com/C6r2pGn.png",
        "SAI": "https://imgur.com/Kkv0SRG.png",
        "DANZO": "https://imgur.com/RTxqZ9p.png",
        "HIRUZEN": "https://imgur.com/oEPqNho.png",
        "SAKURA": "https://imgur.com/ZOwAuHK.png",
        "KABUTO": "https://imgur.com/8x4kRtG.png",
        "GAARA": "https://imgur.com/Tszud9g.png",
        "PAIN": "https://imgur.com/uSsESFD.png",
        "SHIKAMARU": "https://imgur.com/rbaMU3Q.png",
        "ROCK LEE": "https://imgur.com/5KIGo3B.png",
        "KONAN": "https://imgur.com/lCHBPMM.png",
        "TEMARI": "https://imgur.com/xMavYUe.png",
        "INO": "https://imgur.com/swmL40J.png",
        "DEIDARA": "https://imgur.com/MD2DKu4.png",
        "NEJI": "https://imgur.com/4SXuEMM.png",
        "KUSHINA": "https://imgur.com/1uOhKwJ.png",
        "SASORI": "https://imgur.com/0vebREE.png",
        "GAI": "https://imgur.com/vnEBjtI.png",
        "HIDEN": "https://imgur.com/UrQC6uU.png",
        "TENTEN": "https://imgur.com/1HadYOG.png",
        "MEI": "https://imgur.com/01zhgxJ.png",
        "NAGATO": "https://imgur.com/RK5JdMa.png",
        "KISAME": "https://imgur.com/fN8lMHI.png",
        "CHOJI": "https://imgur.com/H0SdMlc.png",
        "ASUMA": "https://imgur.com/kBz1SEj.png",
        "KONOHAMARU": "https://imgur.com/IgJY07U.png",
        "ZABUZA": "https://imgur.com/qHpMEKx.png",
        "KURAMA": "https://imgur.com/oNO2R2Q.png",
        "KILLER BEE": "https://imgur.com/4thjXgr.png",
        "HANABI": "https://imgur.com/jgmtMXU.png",
        "HAKU": "https://imgur.com/sixARLF.png",
        "KAKUZU": "https://imgur.com/nDSpDII.png",
        "SUIGETSU": "https://imgur.com/gqwW1CD.png",
        "KIMIMARO": "https://imgur.com/tgADAbb.png",
        "ZETSU": "https://imgur.com/qdmI11G.png",
        "KANKURO": "https://imgur.com/rqHUvi9.png",
        "JUGO": "https://imgur.com/hUrteHs.png"
    },
    "OnePiece": {
        "LUFFY": "https://i.imgur.com/EXAMPLE4.webp",
        "ZORO": "https://i.imgur.com/EXAMPLE5.webp"
    },
    "Dbz": {
        "GOKU": "https://i.imgur.com/EXAMPLE6.webp"
    },
    "HxH": {},
    "Snk": {},
    "BlackClover": {},
    "Pokemon": {},
    "Bleach": {},
    "DemonSlayer": {},
    "Reborn": {},
    "DeathNote": {},
    "FairyTail": {},
    "JujutsuKaisen": {},
    "ChainsawMan": {},
    "Gintama": {},
    "Prota": {},
    "Fma": {},
    "Mha": {},
    "Jojo": {}
}
